asciify/__init__.py
asciify/__main__.py
asciify/cli.py
asciify/core.py
asciify/process.py
asciify/renderer.py
asciify/utils.py
asciify_them-1.0.3.dist-info/licenses/LICENSE
asciify_them-1.0.3.dist-info/METADATA
asciify_them-1.0.3.dist-info/WHEEL
asciify_them-1.0.3.dist-info/entry_points.txt
asciify_them-1.0.3.dist-info/top_level.txt
asciify_them-1.0.3.dist-info/RECORD
