Metadata-Version: 2.4
Name: asciify-them
Version: 1.0.3
Author-email: Andrea Scalia <andrea95scalia@gmail.com>
License-Expression: MIT
Project-URL: Homepage, https://github.com/ndrscalia/asciify-them
Project-URL: Documentation, https://asciify-them.readthedocs.io/en/latest/
Project-URL: Issues, https://github.com/ndrscalia/asciify-them/issues
Keywords: ASCII art,CLI
Classifier: Development Status :: 3 - Alpha
Classifier: Intended Audience :: Developers
Classifier: Programming Language :: Python :: 3
Classifier: Programming Language :: Python :: 3.9
Classifier: Programming Language :: Python :: 3.10
Classifier: Programming Language :: Python :: 3.11
Classifier: Programming Language :: Python :: 3.12
Classifier: Programming Language :: Python :: 3.13
Classifier: Programming Language :: Python :: 3.14
Requires-Python: >3.9
License-File: LICENSE
Requires-Dist: contourpy==1.3.3
Requires-Dist: cycler==0.12.1
Requires-Dist: fonttools==4.60.1
Requires-Dist: kiwisolver==1.4.9
Requires-Dist: numpy==2.2.6
Requires-Dist: opencv-python==4.12.0.88
Requires-Dist: packaging==25.0
Requires-Dist: pyparsing==3.2.5
Requires-Dist: python-dateutil==2.9.0.post0
Requires-Dist: six==1.17.0
Provides-Extra: dev
Requires-Dist: pytest>=7.0; extra == "dev"
Requires-Dist: pytest-cov>=4.0; extra == "dev"
Requires-Dist: ruff>=0.14.10; extra == "dev"
Dynamic: license-file
